AAD/AAD.py
AAD/AADFunction.py
AAD/AADUtils.py
AAD/AADVariable.py
AAD/__init__.py
aad_jimmielin-1.1.1.dist-info/LICENSE
aad_jimmielin-1.1.1.dist-info/METADATA
aad_jimmielin-1.1.1.dist-info/WHEEL
aad_jimmielin-1.1.1.dist-info/top_level.txt
aad_jimmielin-1.1.1.dist-info/RECORD
