Metadata-Version: 2.1
Name: aad-jimmielin
Version: 1.1.1
Summary: Awesome Automatic Differentiation Project
Home-page: https://github.com/dist-computing/cs107-FinalProject
Author: CS107-Dist-Computing-Group
Author-email: hplin@seas.harvard.edu
License: UNKNOWN
Platform: UNKNOWN
Classifier: Programming Language :: Python :: 3
Classifier: License :: OSI Approved :: MIT License
Classifier: Operating System :: OS Independent
Requires-Python: >=3.6
Requires-Dist: numpy
Requires-Dist: scipy
Requires-Dist: pytest
